paicrypto/__init__.py
paicrypto/main.py
paicrypto-6.0.dist-info/LICENSE
paicrypto-6.0.dist-info/METADATA
paicrypto-6.0.dist-info/WHEEL
paicrypto-6.0.dist-info/top_level.txt
paicrypto-6.0.dist-info/RECORD
