Metadata-Version: 2.1
Name: paicrypto
Version: 6.0
Summary: A collection of algorithms
Home-page: UNKNOWN
Author: Adithya Pai B
Author-email: paiadithya26@gmail.com
License: UNKNOWN
Platform: UNKNOWN
Requires-Dist: pycryptodome
